{"cameraMode":{"drawMode":0,"name":"Shaded","section":"Shading Mode"},"sceneLighting":true,"audioPlay":false,"sceneViewState":{"m_AlwaysRefresh":false,"showFog":true,"showSkybox":true,"showFlares":true,"showImageEffects":true,"showParticleSystems":true,"showVisualEffectGraphs":true,"m_FxEnabled":true},"in2DMode":false,"pivot":{"x":0.0017389506101608277,"y":0.014541864395141602,"z":-0.014350056648254395},"rotation":{"x":0.11888057738542557,"y":0.7983230948448181,"z":-0.16765406727790833,"w":0.5660772323608398},"size":1.8866026401519776,"orthographic":false}